ecl/kenzo.fas
ecl/maxima.fas
passagemath_ecl/__init__.py
passagemath_ecl.libs/libecl-66d0c76c.so.24.5.10
passagemath_ecl.libs/libffi-21f9001b.so.8.1.4
passagemath_ecl.libs/libgc-8b05b29f.so.1.5.4
passagemath_ecl.libs/libgmp-93ebf16a.so.10.5.0
sage/all__sagemath_ecl.py
sage/interfaces/all__sagemath_ecl.py
sage/interfaces/lisp.py
sage/libs/all__sagemath_ecl.py
sage/libs/ecl.cpython-314t-aarch64-linux-gnu.so
sage/libs/ecl.pxd
sage/libs/ecl.pyx
sage/libs/eclsig.h
sage_wheels/bin/ecl
sage_wheels/lib/ecl-24.5.10/COPYING
sage_wheels/lib/ecl-24.5.10/LICENSE
sage_wheels/lib/ecl-24.5.10/TAGS
sage_wheels/lib/ecl-24.5.10/asdf.fas
sage_wheels/lib/ecl-24.5.10/build-stamp
sage_wheels/lib/ecl-24.5.10/cmp.asd
sage_wheels/lib/ecl-24.5.10/cmp.fas
sage_wheels/lib/ecl-24.5.10/deflate.asd
sage_wheels/lib/ecl-24.5.10/deflate.fas
sage_wheels/lib/ecl-24.5.10/defsystem.asd
sage_wheels/lib/ecl-24.5.10/defsystem.fas
sage_wheels/lib/ecl-24.5.10/dpp
sage_wheels/lib/ecl-24.5.10/ecl-cdb.asd
sage_wheels/lib/ecl-24.5.10/ecl-cdb.fas
sage_wheels/lib/ecl-24.5.10/ecl-curl.asd
sage_wheels/lib/ecl-24.5.10/ecl-curl.fas
sage_wheels/lib/ecl-24.5.10/ecl-help.asd
sage_wheels/lib/ecl-24.5.10/ecl-help.fas
sage_wheels/lib/ecl-24.5.10/ecl-quicklisp.asd
sage_wheels/lib/ecl-24.5.10/ecl-quicklisp.fas
sage_wheels/lib/ecl-24.5.10/ecl_min
sage_wheels/lib/ecl-24.5.10/help.doc
sage_wheels/lib/ecl-24.5.10/libasdf.a
sage_wheels/lib/ecl-24.5.10/libcmp.a
sage_wheels/lib/ecl-24.5.10/libdeflate.a
sage_wheels/lib/ecl-24.5.10/libdefsystem.a
sage_wheels/lib/ecl-24.5.10/libecl-cdb.a
sage_wheels/lib/ecl-24.5.10/libecl-curl.a
sage_wheels/lib/ecl-24.5.10/libecl-help.a
sage_wheels/lib/ecl-24.5.10/libecl-quicklisp.a
sage_wheels/lib/ecl-24.5.10/libpackage-locks.a
sage_wheels/lib/ecl-24.5.10/libql-minitar.a
sage_wheels/lib/ecl-24.5.10/libsb-bsd-sockets.a
sage_wheels/lib/ecl-24.5.10/libserve-event.a
sage_wheels/lib/ecl-24.5.10/libsockets.a
sage_wheels/lib/ecl-24.5.10/package-locks.asd
passagemath_ecl-10.6.43.dist-info/METADATA
passagemath_ecl-10.6.43.dist-info/METADATA.bak
passagemath_ecl-10.6.43.dist-info/WHEEL
passagemath_ecl-10.6.43.dist-info/top_level.txt
passagemath_ecl-10.6.43.dist-info/RECORD
